marathon_cli/__init__.py
marathon_cli/exceptions.py
marathon_cli/settings.py
marathon_cli/utils.py
marathon_cli/x.py
marathon_cli/commands/__init__.py
marathon_cli/commands/app-ids.py
marathon_cli/commands/app-tasks.py
marathon_cli/commands/app-versions.py
marathon_cli/commands/apps.py
marathon_cli/commands/delete-app-tasks.py
marathon_cli/commands/delete-app.py
marathon_cli/commands/delete-tasks.py
marathon_cli/commands/put-app.py
marathon_cli/commands/raw.py
marathon_cli/commands/restart-app.py
marathon_cli/commands/tasks.py
marathon_cli-1.1.6.dist-info/DESCRIPTION.rst
marathon_cli-1.1.6.dist-info/METADATA
marathon_cli-1.1.6.dist-info/RECORD
marathon_cli-1.1.6.dist-info/WHEEL
marathon_cli-1.1.6.dist-info/entry_points.txt
marathon_cli-1.1.6.dist-info/metadata.json
marathon_cli-1.1.6.dist-info/top_level.txt
tests/__init__.py
tests/integration/__init__.py
tests/unit/__init__.py
tests/unit/test_cli.py
