Metadata-Version: 2.0
Name: marathon-cli
Version: 1.1.6
Summary: command line utility for marathon api requests
Home-page: https://github.com/meganlkm/marathon-cli
Author: meganlkm
Author-email: megan.lkm@gmail.com
License: MIT
Keywords: mesos,marathon,utility
Platform: UNKNOWN
Classifier: Development Status :: 4 - Beta
Classifier: Intended Audience :: Developers
Classifier: License :: OSI Approved :: MIT License
Classifier: Programming Language :: Python
Classifier: Topic :: System :: Software Distribution
Classifier: Topic :: Utilities
Requires-Dist: click (==6.6)
Requires-Dist: Jinja2 (==2.8)
Requires-Dist: jmespath (==0.9.0)
Requires-Dist: pretty-json (==1.0.1)
Requires-Dist: requests (==2.11.1)
Requires-Dist: spylogger[pretty] (==1.1.2)
